msr/__init__.py
msr/commands.py
msr/config.py
msr/io.py
msr/main.py
msr/net.py
msr/parallel.py
msr/parsing.py
msr/storage.py
mattccs_msr-1.0.0.dist-info/METADATA
mattccs_msr-1.0.0.dist-info/WHEEL
mattccs_msr-1.0.0.dist-info/entry_points.txt
mattccs_msr-1.0.0.dist-info/top_level.txt
mattccs_msr-1.0.0.dist-info/RECORD
