Metadata-Version: 2.1
Name: mattccs-msr
Version: 1.0.0
Summary: Sym 2021 Coding Challenge
Home-page: https://github.com/MattCCS/mattccs-msr
Author: Matt Cotton
Author-email: matthewcotton.cs@gmail.com
License: UNKNOWN
Platform: UNKNOWN
Classifier: Programming Language :: Python :: 3
Requires-Dist: validators
Requires-Dist: requests
Requires-Dist: tabulate
Requires-Dist: tldextract
